torch_sparse/__init__.py
torch_sparse/_convert_cpu.so
torch_sparse/_convert_cuda.so
torch_sparse/_diag_cpu.so
torch_sparse/_diag_cuda.so
torch_sparse/_ego_sample_cpu.so
torch_sparse/_ego_sample_cuda.so
torch_sparse/_hgt_sample_cpu.so
torch_sparse/_hgt_sample_cuda.so
torch_sparse/_metis_cpu.so
torch_sparse/_metis_cuda.so
torch_sparse/_neighbor_sample_cpu.so
torch_sparse/_neighbor_sample_cuda.so
torch_sparse/_relabel_cpu.so
torch_sparse/_relabel_cuda.so
torch_sparse/_rw_cpu.so
torch_sparse/_rw_cuda.so
torch_sparse/_saint_cpu.so
torch_sparse/_saint_cuda.so
torch_sparse/_sample_cpu.so
torch_sparse/_sample_cuda.so
torch_sparse/_spmm_cpu.so
torch_sparse/_spmm_cuda.so
torch_sparse/_version_cpu.so
torch_sparse/_version_cuda.so
torch_sparse/add.py
torch_sparse/bandwidth.py
torch_sparse/cat.py
torch_sparse/coalesce.py
torch_sparse/convert.py
torch_sparse/diag.py
torch_sparse/eye.py
torch_sparse/index_select.py
torch_sparse/masked_select.py
torch_sparse/matmul.py
torch_sparse/metis.py
torch_sparse/mul.py
torch_sparse/narrow.py
torch_sparse/permute.py
torch_sparse/reduce.py
torch_sparse/rw.py
torch_sparse/saint.py
torch_sparse/sample.py
torch_sparse/select.py
torch_sparse/spadd.py
torch_sparse/spmm.py
torch_sparse/spspmm.py
torch_sparse/storage.py
torch_sparse/tensor.py
torch_sparse/testing.py
torch_sparse/transpose.py
torch_sparse/typing.py
torch_sparse/utils.py
torch_sparse_rocm-0.6.18.post2.dist-info/LICENSE
torch_sparse_rocm-0.6.18.post2.dist-info/METADATA
torch_sparse_rocm-0.6.18.post2.dist-info/RECORD
torch_sparse_rocm-0.6.18.post2.dist-info/WHEEL
torch_sparse_rocm-0.6.18.post2.dist-info/top_level.txt